<step title="BackgroundTrace" date="2025-11-10T01:14:39.329" instance="aa3938" url="/api/zipdeploy" method="POST" >
  <step title="Cleanup Xml Logs" date="2025-11-10T01:14:39.341" /><!-- duration: 5ms -->
  <step title="Creating temporary deployment - FetchDeploymentManager" date="2025-11-10T01:14:39.481" /><!-- duration: 3ms -->
  <step title="Creating temporary deployment" date="2025-11-10T01:14:39.488" /><!-- duration: 89ms -->
  <step title="Performing fetch based deployment" date="2025-11-10T01:14:39.689" >
    <step title="Cleaning up temp folders from previous zip deployments and extracting pushed zip file /tmp/zipdeploy/bb4a60d5-ffe0-4cca-9dce-4fe5134b5afe.zip (25.32 MB) to /tmp/zipdeploy/extracted" date="2025-11-10T01:14:40.932" >
      <step title="ChmodRecursive Process exited with total time taken in ms: 582" date="2025-11-10T01:14:56.180" /><!-- duration: 5ms -->
    </step><!-- duration: 15339ms -->
    <step title="Deployment timer started" date="2025-11-10T01:14:58.298" >
      <step title="DeploymentManager.Deploy(id:c3ddc1a2-159b-45ff-b08a-e4e389b30f9c)" date="2025-11-10T01:14:58.304" >
        <step title="Collecting changeset information" date="2025-11-10T01:14:58.354" /><!-- duration: 252ms -->
        <step title="Updating submodules" date="2025-11-10T01:14:58.611" /><!-- duration: 1226ms -->
        <step title="Determining deployment builder" date="2025-11-10T01:15:00.234" >
          <step title="Builder is OryxBuilder" date="2025-11-10T01:15:00.264" /><!-- duration: 2ms -->
        </step><!-- duration: 35ms -->
        <step title="PreDeployment: context.CleanOutputPath False" date="2025-11-10T01:15:00.341" >
          <step title="PreDeployment: context.OutputPath /home/site/wwwroot" date="2025-11-10T01:15:00.516" >
            <step title="Building" date="2025-11-10T01:15:00.717" >
              <step title="Executing external process" date="2025-11-10T01:15:01.260" type="process" path="bash" arguments="-c &quot;oryx build /tmp/zipdeploy/extracted -o /home/site/wwwroot --platform python --platform-version 3.12 -p virtualenv_name=antenv --log-file /tmp/build-debug.log  -i /tmp/8de1ff691dc75f4 --compress-destination-dir | tee /tmp/oryx-build.log ; exit $PIPESTATUS &quot;" /><!-- duration: 186662ms -->
              <step title="Using PythonDeploymentLogParser" date="2025-11-10T01:18:08.669" /><!-- duration: 3ms -->
              <step title="Triggering recycle (preview mode disabled)." date="2025-11-10T01:18:10.383" /><!-- duration: 10ms -->
              <step title="Modified file to trigger a restart of the app container." date="2025-11-10T01:18:10.441" /><!-- duration: 2ms -->
              <step title="Skip function trigger and logicapp sync because function is not enabled." date="2025-11-10T01:18:10.453" /><!-- duration: 20ms -->
            </step><!-- duration: 190880ms -->
          </step><!-- duration: 191086ms -->
          <step title="Cleaning up temp files" date="2025-11-10T01:18:11.603" /><!-- duration: 3612ms -->
          <step title="Cleaning up temp files" date="2025-11-10T01:18:15.226" /><!-- duration: 551ms -->
          <step title="Reloading status file with latest updates" date="2025-11-10T01:18:15.807" >
            <step title="WebHooksManager.PublishEventAsync: PostDeployment" date="2025-11-10T01:18:15.810" /><!-- duration: 102ms -->
          </step><!-- duration: 118ms -->
          <step title="Cleaning up temporary deployment - fetch deployment was successful" date="2025-11-10T01:18:15.929" /><!-- duration: 2ms -->
        </step><!-- duration: 195654ms -->
      </step><!-- duration: 197705ms -->
